eotile/__init__.py
eotile/eotile_cli.py
eotile/eotile_module.py
eotile/config/data_path
eotile/data/aux_data/DEM_Union.gpkg
eotile/data/aux_data/DEM_Union_source.md
eotile/data/aux_data/l8_tiles.gpkg
eotile/data/aux_data/s2_no_overlap.gpkg
eotile/data/aux_data/s2_with_overlap.gpkg
eotile/data/aux_data/srtm5x5_tiles.gpkg
eotile/data/aux_data/sources/readme.md
eotile/data/aux_data/sources/xml_s2_output.log
eotile/eotiles/__init__.py
eotile/eotiles/eotiles.py
eotile/eotiles/get_bb_from_tile_id.py
eotile/eotiles/utils.py
eotile-0.2.8.dist-info/LICENSE
eotile-0.2.8.dist-info/METADATA
eotile-0.2.8.dist-info/NOTICE
eotile-0.2.8.dist-info/WHEEL
eotile-0.2.8.dist-info/entry_points.txt
eotile-0.2.8.dist-info/top_level.txt
eotile-0.2.8.dist-info/RECORD
