Metadata-Version: 2.1
Name: eotile
Version: 0.2.8
Summary: Managed Sentinel-2 and Landsat8 tile
Home-page: https://github.com/CS-SI/eotile
Author: Mickaël Savinaud, Mathis A. Germa
Author-email: mickael.savinaud@csgroup.eu, mathis.germa@csgroup.eu
License: Apache License Version 2.0
Classifier: Programming Language :: Python :: 3
Classifier: License :: OSI Approved :: Apache Software License
Classifier: Operating System :: OS Independent
Requires-Python: >=3.6, <4
License-File: LICENSE
License-File: NOTICE
Requires-Dist: geopandas (<0.10,>=0.9)
Requires-Dist: geopy (<3,>=2.2)
Requires-Dist: pyproj (<4,>=3)
Requires-Dist: requests (<3,>=2.26)
Requires-Dist: Shapely (<2,>=1.8)
Provides-Extra: dev
Requires-Dist: check-manifest ; extra == 'dev'
Provides-Extra: test
Requires-Dist: coverage (<=6,>5) ; extra == 'test'
